{
  "format-version" : 2,
  "table-uuid" : "b8fcdbb3-be04-4feb-8f12-881968a8c90a",
  "location" : "s3://mns-iceberg-demo/flights",
  "last-sequence-number" : 1,
  "last-updated-ms" : 1741789432335,
  "last-column-id" : 4,
  "current-schema-id" : 0,
  "schemas" : [ {
    "type" : "struct",
    "schema-id" : 0,
    "fields" : [ {
      "id" : 1,
      "name" : "departure_delay",
      "required" : false,
      "type" : "double"
    }, {
      "id" : 2,
      "name" : "arrival_delay",
      "required" : false,
      "type" : "long"
    }, {
      "id" : 3,
      "name" : "distance",
      "required" : false,
      "type" : "long"
    }, {
      "id" : 4,
      "name" : "scheduled_departure",
      "required" : false,
      "type" : "double"
    } ]
  } ],
  "default-spec-id" : 0,
  "partition-specs" : [ {
    "spec-id" : 0,
    "fields" : [ {
      "name" : "arrival_delay_bucket",
      "transform" : "bucket[10]",
      "source-id" : 2,
      "field-id" : 1000
    } ]
  } ],
  "last-partition-id" : 1000,
  "default-sort-order-id" : 0,
  "sort-orders" : [ {
    "order-id" : 0,
    "fields" : [ ]
  } ],
  "properties" : {
    "write.object-storage.enabled" : "true",
    "write.object-storage.path" : "s3://mns-iceberg-demo/flights/data",
    "write.parquet.compression-codec" : "zstd"
  },
  "current-snapshot-id" : 4238556914976270217,
  "refs" : {
    "main" : {
      "snapshot-id" : 4238556914976270217,
      "type" : "branch"
    }
  },
  "snapshots" : [ {
    "sequence-number" : 1,
    "snapshot-id" : 4238556914976270217,
    "timestamp-ms" : 1741789432335,
    "summary" : {
      "operation" : "append",
      "trino_query_id" : "20250312_142346_00079_dqik5",
      "added-data-files" : "11",
      "added-records" : "5819079",
      "added-files-size" : "16663023",
      "changed-partition-count" : "11",
      "total-records" : "5819079",
      "total-files-size" : "16663023",
      "total-data-files" : "11",
      "total-delete-files" : "0",
      "total-position-deletes" : "0",
      "total-equality-deletes" : "0"
    },
    "manifest-list" : "s3://mns-iceberg-demo/flights/metadata/snap-4238556914976270217-1-b04c4259-d13f-4032-bc83-87070e6598ab.avro",
    "schema-id" : 0
  } ],
  "statistics" : [ ],
  "snapshot-log" : [ {
    "timestamp-ms" : 1741789432335,
    "snapshot-id" : 4238556914976270217
  } ],
  "metadata-log" : [ {
    "timestamp-ms" : 1741789359779,
    "metadata-file" : "s3://mns-iceberg-demo/flights/metadata/00000-cb125778-6b53-4cde-be4e-1c87ff66af2a.metadata.json"
  } ]
}